<root>
    <item name='android.support.v7.widget.SnapHelper int findTargetSnapPosition(android.support.v7.widget.RecyclerView.LayoutManager, int, int) 0'>
        <annotation name='org.jetbrains.annotations.NotNull'/>
        <annotation name='org.jetbrains.kannotator.runtime.annotations.Propagated'>
            <val name="value" val="{org.jetbrains.kannotator.controlFlow.builder.analysis.NullabilityKey.class}"/>
        </annotation>
    </item>
    <item name='android.support.v7.widget.RecyclerView.ItemAnimator android.support.v7.widget.RecyclerView.ItemAnimator.ItemHolderInfo recordPreLayoutInformation(android.support.v7.widget.RecyclerView.State, android.support.v7.widget.RecyclerView.ViewHolder, int, java.util.List&lt;java.lang.Object&gt;) 1'>
        <annotation name='org.jetbrains.annotations.NotNull'/>
    </item>
    <item name='android.support.v7.widget.RecyclerView.ItemAnimator boolean animateChange(android.support.v7.widget.RecyclerView.ViewHolder, android.support.v7.widget.RecyclerView.ViewHolder, android.support.v7.widget.RecyclerView.ItemAnimator.ItemHolderInfo, android.support.v7.widget.RecyclerView.ItemAnimator.ItemHolderInfo) 2'>
        <annotation name='org.jetbrains.annotations.NotNull'/>
        <annotation name='org.jetbrains.kannotator.runtime.annotations.Propagated'>
            <val name="value" val="{org.jetbrains.kannotator.controlFlow.builder.analysis.NullabilityKey.class}"/>
        </annotation>
    </item>
    <item name='android.support.v7.widget.StaggeredGridLayoutManager int[] findFirstVisibleItemPositions(int[])'>
        <annotation name='org.jetbrains.annotations.NotNull'/>
    </item>
    <item name='android.support.v7.widget.GridLayoutManager android.support.v7.widget.RecyclerView.LayoutParams generateLayoutParams(android.content.Context, android.util.AttributeSet)'>
        <annotation name='org.jetbrains.annotations.NotNull'/>
    </item>
    <item name='android.support.v7.widget.RecyclerView.OnScrollListener void onScrolled(android.support.v7.widget.RecyclerView, int, int) 0'>
        <annotation name='org.jetbrains.annotations.NotNull'/>
        <annotation name='org.jetbrains.kannotator.runtime.annotations.Propagated'>
            <val name="value" val="{org.jetbrains.kannotator.controlFlow.builder.analysis.NullabilityKey.class}"/>
        </annotation>
    </item>
    <item name='android.support.v7.widget.RecyclerView.ItemDecoration void getItemOffsets(android.graphics.Rect, android.view.View, android.support.v7.widget.RecyclerView, android.support.v7.widget.RecyclerView.State) 1'>
        <annotation name='org.jetbrains.annotations.NotNull'/>
    </item>
    <item name='android.support.v7.widget.DefaultItemAnimator boolean animateChange(android.support.v7.widget.RecyclerView.ViewHolder, android.support.v7.widget.RecyclerView.ViewHolder, int, int, int, int) 0'>
        <annotation name='org.jetbrains.annotations.NotNull'/>
    </item>
    <item name='android.support.v7.widget.OrientationHelper int getTransformedStartWithDecoration(android.view.View) 0'>
        <annotation name='org.jetbrains.annotations.NotNull'/>
        <annotation name='org.jetbrains.kannotator.runtime.annotations.Propagated'>
            <val name="value" val="{org.jetbrains.kannotator.controlFlow.builder.analysis.NullabilityKey.class}"/>
        </annotation>
    </item>
    <item name='android.support.v7.widget.StaggeredGridLayoutManager void smoothScrollToPosition(android.support.v7.widget.RecyclerView, android.support.v7.widget.RecyclerView.State, int) 0'>
        <annotation name='org.jetbrains.annotations.NotNull'/>
    </item>
    <item name='android.support.v7.widget.LinearSmoothScroller mLinearInterpolator'>
        <annotation name='org.jetbrains.annotations.NotNull'/>
    </item>
    <item name='android.support.v7.widget.RecyclerView.ItemAnimator boolean animateDisappearance(android.support.v7.widget.RecyclerView.ViewHolder, android.support.v7.widget.RecyclerView.ItemAnimator.ItemHolderInfo, android.support.v7.widget.RecyclerView.ItemAnimator.ItemHolderInfo) 1'>
        <annotation name='org.jetbrains.annotations.NotNull'/>
        <annotation name='org.jetbrains.kannotator.runtime.annotations.Propagated'>
            <val name="value" val="{org.jetbrains.kannotator.controlFlow.builder.analysis.NullabilityKey.class}"/>
        </annotation>
    </item>
    <item name='android.support.v7.widget.RecyclerViewAccessibilityDelegate android.support.v4.view.AccessibilityDelegateCompat getItemDelegate()'>
        <annotation name='org.jetbrains.annotations.NotNull'/>
    </item>
    <item name='android.support.v7.widget.RecyclerView void getDecoratedBoundsWithMargins(android.view.View, android.graphics.Rect) 0'>
        <annotation name='org.jetbrains.annotations.NotNull'/>
    </item>
    <item name='android.support.v7.widget.RecyclerViewAccessibilityDelegate void onInitializeAccessibilityNodeInfo(android.view.View, android.support.v4.view.accessibility.AccessibilityNodeInfoCompat) 1'>
        <annotation name='org.jetbrains.annotations.NotNull'/>
    </item>
    <item name='android.support.v7.widget.GridLayoutManager void onInitializeAccessibilityNodeInfoForItem(android.support.v7.widget.RecyclerView.Recycler, android.support.v7.widget.RecyclerView.State, android.view.View, android.support.v4.view.accessibility.AccessibilityNodeInfoCompat) 2'>
        <annotation name='org.jetbrains.annotations.NotNull'/>
    </item>
    <item name='android.support.v7.widget.RecyclerView.ItemAnimator boolean animateChange(android.support.v7.widget.RecyclerView.ViewHolder, android.support.v7.widget.RecyclerView.ViewHolder, android.support.v7.widget.RecyclerView.ItemAnimator.ItemHolderInfo, android.support.v7.widget.RecyclerView.ItemAnimator.ItemHolderInfo) 1'>
        <annotation name='org.jetbrains.annotations.NotNull'/>
        <annotation name='org.jetbrains.kannotator.runtime.annotations.Propagated'>
            <val name="value" val="{org.jetbrains.kannotator.controlFlow.builder.analysis.NullabilityKey.class}"/>
        </annotation>
    </item>
    <item name='android.support.v7.widget.RecyclerView.LayoutManager void smoothScrollToPosition(android.support.v7.widget.RecyclerView, android.support.v7.widget.RecyclerView.State, int) 0'>
        <annotation name='org.jetbrains.annotations.NotNull'/>
        <annotation name='org.jetbrains.kannotator.runtime.annotations.Propagated'>
            <val name="value" val="{org.jetbrains.kannotator.controlFlow.builder.analysis.NullabilityKey.class}"/>
        </annotation>
    </item>
    <item name='android.support.v7.widget.RecyclerView android.support.v7.widget.RecyclerView.ViewHolder findContainingViewHolder(android.view.View) 0'>
        <annotation name='org.jetbrains.annotations.NotNull'/>
    </item>
    <item name='android.support.v7.widget.RecyclerView.LayoutManager void layoutDecorated(android.view.View, int, int, int, int) 0'>
        <annotation name='org.jetbrains.annotations.NotNull'/>
    </item>
    <item name='android.support.v7.widget.RecyclerView.LayoutManager void addDisappearingView(android.view.View, int) 0'>
        <annotation name='org.jetbrains.annotations.NotNull'/>
    </item>
    <item name='android.support.v7.widget.RecyclerView.LayoutManager int getDecoratedLeft(android.view.View) 0'>
        <annotation name='org.jetbrains.annotations.NotNull'/>
    </item>
    <item name='android.support.v7.widget.RecyclerView.LayoutManager void getTransformedBoundingBox(android.view.View, boolean, android.graphics.Rect) 0'>
        <annotation name='org.jetbrains.annotations.NotNull'/>
    </item>
    <item name='android.support.v7.widget.RecyclerView.LayoutManager void removeAndRecycleView(android.view.View, android.support.v7.widget.RecyclerView.Recycler) 1'>
        <annotation name='org.jetbrains.annotations.NotNull'/>
    </item>
    <item name='android.support.v7.widget.StaggeredGridLayoutManager void onLayoutChildren(android.support.v7.widget.RecyclerView.Recycler, android.support.v7.widget.RecyclerView.State) 1'>
        <annotation name='org.jetbrains.annotations.NotNull'/>
    </item>
    <item name='android.support.v7.widget.RecyclerView.SavedState void writeToParcel(android.os.Parcel, int) 0'>
        <annotation name='org.jetbrains.annotations.NotNull'/>
    </item>
    <item name='android.support.v7.widget.RecyclerView.LayoutManager boolean requestChildRectangleOnScreen(android.support.v7.widget.RecyclerView, android.view.View, android.graphics.Rect, boolean) 1'>
        <annotation name='org.jetbrains.annotations.NotNull'/>
    </item>
    <item name='android.support.v7.widget.DividerItemDecoration void getItemOffsets(android.graphics.Rect, android.view.View, android.support.v7.widget.RecyclerView, android.support.v7.widget.RecyclerView.State) 0'>
        <annotation name='org.jetbrains.annotations.NotNull'/>
    </item>
    <item name='android.support.v7.widget.RecyclerView.Adapter void bindViewHolder(VH, int) 0'>
        <annotation name='org.jetbrains.annotations.NotNull'/>
    </item>
    <item name='android.support.v7.widget.DividerItemDecoration void onDraw(android.graphics.Canvas, android.support.v7.widget.RecyclerView, android.support.v7.widget.RecyclerView.State) 1'>
        <annotation name='org.jetbrains.annotations.NotNull'/>
    </item>
    <item name='android.support.v7.widget.RecyclerView.LayoutManager android.support.v7.widget.RecyclerView.LayoutManager.Properties getProperties(android.content.Context, android.util.AttributeSet, int, int) 0'>
        <annotation name='org.jetbrains.annotations.NotNull'/>
    </item>
    <item name='android.support.v7.widget.RecyclerView.SimpleOnItemTouchListener boolean onInterceptTouchEvent(android.support.v7.widget.RecyclerView, android.view.MotionEvent) 1'>
        <annotation name='org.jetbrains.annotations.NotNull'/>
        <annotation name='org.jetbrains.kannotator.runtime.annotations.Propagated'>
            <val name="value" val="{org.jetbrains.kannotator.controlFlow.builder.analysis.NullabilityKey.class}"/>
        </annotation>
    </item>
    <item name='android.support.v7.widget.RecyclerView.ItemAnimator.ItemHolderInfo android.support.v7.widget.RecyclerView.ItemAnimator.ItemHolderInfo setFrom(android.support.v7.widget.RecyclerView.ViewHolder) 0'>
        <annotation name='org.jetbrains.annotations.NotNull'/>
    </item>
    <item name='android.support.v7.widget.OrientationHelper int getDecoratedMeasurement(android.view.View) 0'>
        <annotation name='org.jetbrains.annotations.NotNull'/>
        <annotation name='org.jetbrains.kannotator.runtime.annotations.Propagated'>
            <val name="value" val="{org.jetbrains.kannotator.controlFlow.builder.analysis.NullabilityKey.class}"/>
        </annotation>
    </item>
    <item name='android.support.v7.widget.RecyclerView.ItemDecoration void getItemOffsets(android.graphics.Rect, android.view.View, android.support.v7.widget.RecyclerView, android.support.v7.widget.RecyclerView.State) 0'>
        <annotation name='org.jetbrains.annotations.NotNull'/>
    </item>
    <item name='android.support.v7.widget.RecyclerView.LayoutManager void removeAndRecycleViewAt(int, android.support.v7.widget.RecyclerView.Recycler) 1'>
        <annotation name='org.jetbrains.annotations.NotNull'/>
    </item>
    <item name='android.support.v7.widget.RecyclerView.ItemAnimator boolean animateDisappearance(android.support.v7.widget.RecyclerView.ViewHolder, android.support.v7.widget.RecyclerView.ItemAnimator.ItemHolderInfo, android.support.v7.widget.RecyclerView.ItemAnimator.ItemHolderInfo) 0'>
        <annotation name='org.jetbrains.annotations.NotNull'/>
        <annotation name='org.jetbrains.kannotator.runtime.annotations.Propagated'>
            <val name="value" val="{org.jetbrains.kannotator.controlFlow.builder.analysis.NullabilityKey.class}"/>
        </annotation>
    </item>
    <item name='android.support.v7.widget.LinearLayoutManager android.os.Parcelable onSaveInstanceState()'>
        <annotation name='org.jetbrains.annotations.NotNull'/>
    </item>
    <item name='android.support.v7.widget.RecyclerView.ItemAnimator android.support.v7.widget.RecyclerView.ItemAnimator.ItemHolderInfo recordPostLayoutInformation(android.support.v7.widget.RecyclerView.State, android.support.v7.widget.RecyclerView.ViewHolder)'>
        <annotation name='org.jetbrains.annotations.NotNull'/>
    </item>
    <item name='android.support.v7.widget.RecyclerView void getDecoratedBoundsWithMargins(android.view.View, android.graphics.Rect) 1'>
        <annotation name='org.jetbrains.annotations.NotNull'/>
    </item>
    <item name='android.support.v7.widget.RecyclerView.ItemAnimator android.support.v7.widget.RecyclerView.ItemAnimator.ItemHolderInfo obtainHolderInfo()'>
        <annotation name='org.jetbrains.annotations.NotNull'/>
    </item>
    <item name='android.support.v7.widget.StaggeredGridLayoutManager.SavedState SavedState(android.support.v7.widget.StaggeredGridLayoutManager.SavedState) 0'>
        <annotation name='org.jetbrains.annotations.NotNull'/>
    </item>
    <item name='android.support.v7.widget.RecyclerView.ItemAnimator.ItemHolderInfo android.support.v7.widget.RecyclerView.ItemAnimator.ItemHolderInfo setFrom(android.support.v7.widget.RecyclerView.ViewHolder, int) 0'>
        <annotation name='org.jetbrains.annotations.NotNull'/>
    </item>
    <item name='android.support.v7.widget.RecyclerView.LayoutManager void layoutDecoratedWithMargins(android.view.View, int, int, int, int) 0'>
        <annotation name='org.jetbrains.annotations.NotNull'/>
    </item>
    <item name='android.support.v7.widget.RecyclerView.LayoutManager void onInitializeAccessibilityNodeInfoForItem(android.support.v7.widget.RecyclerView.Recycler, android.support.v7.widget.RecyclerView.State, android.view.View, android.support.v4.view.accessibility.AccessibilityNodeInfoCompat) 2'>
        <annotation name='org.jetbrains.annotations.NotNull'/>
        <annotation name='org.jetbrains.kannotator.runtime.annotations.Propagated'>
            <val name="value" val="{org.jetbrains.kannotator.controlFlow.builder.analysis.NullabilityKey.class}"/>
        </annotation>
    </item>
    <item name='android.support.v7.widget.DividerItemDecoration DividerItemDecoration(android.content.Context, int) 0'>
        <annotation name='org.jetbrains.annotations.NotNull'/>
    </item>
    <item name='android.support.v7.widget.RecyclerView.ItemAnimator boolean animatePersistence(android.support.v7.widget.RecyclerView.ViewHolder, android.support.v7.widget.RecyclerView.ItemAnimator.ItemHolderInfo, android.support.v7.widget.RecyclerView.ItemAnimator.ItemHolderInfo) 1'>
        <annotation name='org.jetbrains.annotations.NotNull'/>
        <annotation name='org.jetbrains.kannotator.runtime.annotations.Propagated'>
            <val name="value" val="{org.jetbrains.kannotator.controlFlow.builder.analysis.NullabilityKey.class}"/>
        </annotation>
    </item>
    <item name='android.support.v7.widget.RecyclerView.LayoutManager boolean requestChildRectangleOnScreen(android.support.v7.widget.RecyclerView, android.view.View, android.graphics.Rect, boolean, boolean) 2'>
        <annotation name='org.jetbrains.annotations.NotNull'/>
    </item>
    <item name='android.support.v7.widget.RecyclerView.LayoutManager void setMeasuredDimension(android.graphics.Rect, int, int) 0'>
        <annotation name='org.jetbrains.annotations.NotNull'/>
    </item>
    <item name='android.support.v7.widget.SimpleItemAnimator boolean animateMove(android.support.v7.widget.RecyclerView.ViewHolder, int, int, int, int) 0'>
        <annotation name='org.jetbrains.annotations.NotNull'/>
        <annotation name='org.jetbrains.kannotator.runtime.annotations.Propagated'>
            <val name="value" val="{org.jetbrains.kannotator.controlFlow.builder.analysis.NullabilityKey.class}"/>
        </annotation>
    </item>
    <item name='android.support.v7.widget.PagerSnapHelper int[] calculateDistanceToFinalSnap(android.support.v7.widget.RecyclerView.LayoutManager, android.view.View)'>
        <annotation name='org.jetbrains.annotations.NotNull'/>
    </item>
    <item name='android.support.v7.widget.RecyclerView.ItemAnimator.ItemHolderInfo android.support.v7.widget.RecyclerView.ItemAnimator.ItemHolderInfo setFrom(android.support.v7.widget.RecyclerView.ViewHolder, int)'>
        <annotation name='org.jetbrains.annotations.NotNull'/>
    </item>
    <item name='android.support.v7.widget.RecyclerView.LayoutManager int getLeftDecorationWidth(android.view.View) 0'>
        <annotation name='org.jetbrains.annotations.NotNull'/>
    </item>
    <item name='android.support.v7.widget.SimpleItemAnimator boolean animateChange(android.support.v7.widget.RecyclerView.ViewHolder, android.support.v7.widget.RecyclerView.ViewHolder, int, int, int, int) 0'>
        <annotation name='org.jetbrains.annotations.NotNull'/>
        <annotation name='org.jetbrains.kannotator.runtime.annotations.Propagated'>
            <val name="value" val="{org.jetbrains.kannotator.controlFlow.builder.analysis.NullabilityKey.class}"/>
        </annotation>
    </item>
    <item name='android.support.v7.widget.RecyclerView.LayoutManager boolean requestChildRectangleOnScreen(android.support.v7.widget.RecyclerView, android.view.View, android.graphics.Rect, boolean) 2'>
        <annotation name='org.jetbrains.annotations.NotNull'/>
    </item>
    <item name='android.support.v7.widget.DividerItemDecoration void getItemOffsets(android.graphics.Rect, android.view.View, android.support.v7.widget.RecyclerView, android.support.v7.widget.RecyclerView.State) 1'>
        <annotation name='org.jetbrains.annotations.NotNull'/>
        <annotation name='org.jetbrains.kannotator.runtime.annotations.Propagated'>
            <val name="value" val="{org.jetbrains.kannotator.controlFlow.builder.analysis.NullabilityKey.class}"/>
        </annotation>
    </item>
    <item name='android.support.v7.widget.LinearLayoutManager.SavedState SavedState(android.support.v7.widget.LinearLayoutManager.SavedState) 0'>
        <annotation name='org.jetbrains.annotations.NotNull'/>
    </item>
    <item name='android.support.v7.widget.RecyclerView.LayoutManager void calculateItemDecorationsForChild(android.view.View, android.graphics.Rect) 1'>
        <annotation name='org.jetbrains.annotations.NotNull'/>
    </item>
    <item name='android.support.v7.widget.RecyclerView.ViewHolder ViewHolder(android.view.View) 0'>
        <annotation name='org.jetbrains.annotations.NotNull'/>
    </item>
    <item name='android.support.v7.widget.StaggeredGridLayoutManager void setMeasuredDimension(android.graphics.Rect, int, int) 0'>
        <annotation name='org.jetbrains.annotations.NotNull'/>
    </item>
    <item name='android.support.v7.widget.StaggeredGridLayoutManager android.support.v7.widget.RecyclerView.LayoutParams generateLayoutParams(android.content.Context, android.util.AttributeSet)'>
        <annotation name='org.jetbrains.annotations.NotNull'/>
    </item>
    <item name='android.support.v7.widget.SimpleItemAnimator boolean animateChange(android.support.v7.widget.RecyclerView.ViewHolder, android.support.v7.widget.RecyclerView.ViewHolder, android.support.v7.widget.RecyclerView.ItemAnimator.ItemHolderInfo, android.support.v7.widget.RecyclerView.ItemAnimator.ItemHolderInfo) 1'>
        <annotation name='org.jetbrains.annotations.NotNull'/>
    </item>
    <item name='android.support.v7.widget.PagerSnapHelper int findTargetSnapPosition(android.support.v7.widget.RecyclerView.LayoutManager, int, int) 0'>
        <annotation name='org.jetbrains.annotations.NotNull'/>
    </item>
    <item name='android.support.v7.widget.RecyclerView.LayoutManager android.support.v7.widget.RecyclerView.LayoutParams generateDefaultLayoutParams()'>
        <annotation name='org.jetbrains.annotations.NotNull'/>
        <annotation name='org.jetbrains.kannotator.runtime.annotations.Propagated'>
            <val name="value" val="{org.jetbrains.kannotator.controlFlow.builder.analysis.NullabilityKey.class}"/>
        </annotation>
    </item>
    <item name='android.support.v7.widget.StaggeredGridLayoutManager void onInitializeAccessibilityNodeInfoForItem(android.support.v7.widget.RecyclerView.Recycler, android.support.v7.widget.RecyclerView.State, android.view.View, android.support.v4.view.accessibility.AccessibilityNodeInfoCompat) 2'>
        <annotation name='org.jetbrains.annotations.NotNull'/>
    </item>
    <item name='android.support.v7.widget.RecyclerView.LayoutManager int getDecoratedBottom(android.view.View) 0'>
        <annotation name='org.jetbrains.annotations.NotNull'/>
    </item>
    <item name='android.support.v7.widget.RecyclerView.LayoutManager void onInitializeAccessibilityNodeInfo(android.support.v7.widget.RecyclerView.Recycler, android.support.v7.widget.RecyclerView.State, android.support.v4.view.accessibility.AccessibilityNodeInfoCompat) 2'>
        <annotation name='org.jetbrains.annotations.NotNull'/>
    </item>
    <item name='android.support.v7.widget.SimpleItemAnimator boolean animateRemove(android.support.v7.widget.RecyclerView.ViewHolder) 0'>
        <annotation name='org.jetbrains.annotations.NotNull'/>
        <annotation name='org.jetbrains.kannotator.runtime.annotations.Propagated'>
            <val name="value" val="{org.jetbrains.kannotator.controlFlow.builder.analysis.NullabilityKey.class}"/>
        </annotation>
    </item>
    <item name='android.support.v7.widget.StaggeredGridLayoutManager int[] findFirstCompletelyVisibleItemPositions(int[])'>
        <annotation name='org.jetbrains.annotations.NotNull'/>
    </item>
    <item name='android.support.v7.widget.RecyclerView.ItemAnimator boolean animatePersistence(android.support.v7.widget.RecyclerView.ViewHolder, android.support.v7.widget.RecyclerView.ItemAnimator.ItemHolderInfo, android.support.v7.widget.RecyclerView.ItemAnimator.ItemHolderInfo) 2'>
        <annotation name='org.jetbrains.annotations.NotNull'/>
        <annotation name='org.jetbrains.kannotator.runtime.annotations.Propagated'>
            <val name="value" val="{org.jetbrains.kannotator.controlFlow.builder.analysis.NullabilityKey.class}"/>
        </annotation>
    </item>
    <item name='android.support.v7.widget.RecyclerView.SavedState CREATOR'>
        <annotation name='org.jetbrains.annotations.NotNull'/>
    </item>
    <item name='android.support.v7.widget.RecyclerView.ItemAnimator android.support.v7.widget.RecyclerView.ItemAnimator.ItemHolderInfo recordPreLayoutInformation(android.support.v7.widget.RecyclerView.State, android.support.v7.widget.RecyclerView.ViewHolder, int, java.util.List&lt;java.lang.Object&gt;)'>
        <annotation name='org.jetbrains.annotations.NotNull'/>
    </item>
    <item name='android.support.v7.widget.RecyclerView.LayoutManager int getRightDecorationWidth(android.view.View) 0'>
        <annotation name='org.jetbrains.annotations.NotNull'/>
    </item>
    <item name='android.support.v7.widget.RecyclerView.LayoutManager void removeDetachedView(android.view.View) 0'>
        <annotation name='org.jetbrains.annotations.NotNull'/>
    </item>
    <item name='android.support.v7.widget.RecyclerView.LayoutManager void addView(android.view.View, int) 0'>
        <annotation name='org.jetbrains.annotations.NotNull'/>
    </item>
    <item name='android.support.v7.widget.RecyclerView.LayoutManager void measureChildWithMargins(android.view.View, int, int) 0'>
        <annotation name='org.jetbrains.annotations.NotNull'/>
    </item>
    <item name='android.support.v7.widget.DefaultItemAnimator boolean animateRemove(android.support.v7.widget.RecyclerView.ViewHolder) 0'>
        <annotation name='org.jetbrains.annotations.NotNull'/>
    </item>
    <item name='android.support.v7.widget.StaggeredGridLayoutManager.SavedState CREATOR'>
        <annotation name='org.jetbrains.annotations.NotNull'/>
    </item>
    <item name='android.support.v7.widget.StaggeredGridLayoutManager int[] findLastCompletelyVisibleItemPositions(int[])'>
        <annotation name='org.jetbrains.annotations.NotNull'/>
    </item>
    <item name='android.support.v7.widget.LinearLayoutManager void onLayoutChildren(android.support.v7.widget.RecyclerView.Recycler, android.support.v7.widget.RecyclerView.State) 1'>
        <annotation name='org.jetbrains.annotations.NotNull'/>
    </item>
    <item name='android.support.v7.widget.PagerSnapHelper int[] calculateDistanceToFinalSnap(android.support.v7.widget.RecyclerView.LayoutManager, android.view.View) 0'>
        <annotation name='org.jetbrains.annotations.NotNull'/>
    </item>
    <item name='android.support.v7.widget.SimpleItemAnimator boolean animateChange(android.support.v7.widget.RecyclerView.ViewHolder, android.support.v7.widget.RecyclerView.ViewHolder, android.support.v7.widget.RecyclerView.ItemAnimator.ItemHolderInfo, android.support.v7.widget.RecyclerView.ItemAnimator.ItemHolderInfo) 2'>
        <annotation name='org.jetbrains.annotations.NotNull'/>
    </item>
    <item name='android.support.v7.widget.RecyclerView.LayoutManager void ignoreView(android.view.View) 0'>
        <annotation name='org.jetbrains.annotations.NotNull'/>
    </item>
    <item name='android.support.v7.widget.RecyclerView.LayoutManager void onLayoutChildren(android.support.v7.widget.RecyclerView.Recycler, android.support.v7.widget.RecyclerView.State) 1'>
        <annotation name='org.jetbrains.annotations.NotNull'/>
        <annotation name='org.jetbrains.kannotator.runtime.annotations.Propagated'>
            <val name="value" val="{org.jetbrains.kannotator.controlFlow.builder.analysis.NullabilityKey.class}"/>
        </annotation>
    </item>
    <item name='android.support.v7.widget.RecyclerView.RecycledViewPool void putRecycledView(android.support.v7.widget.RecyclerView.ViewHolder) 0'>
        <annotation name='org.jetbrains.annotations.NotNull'/>
    </item>
    <item name='android.support.v7.widget.StaggeredGridLayoutManager void onInitializeAccessibilityNodeInfoForItem(android.support.v7.widget.RecyclerView.Recycler, android.support.v7.widget.RecyclerView.State, android.view.View, android.support.v4.view.accessibility.AccessibilityNodeInfoCompat) 3'>
        <annotation name='org.jetbrains.annotations.NotNull'/>
        <annotation name='org.jetbrains.kannotator.runtime.annotations.Propagated'>
            <val name="value" val="{org.jetbrains.kannotator.controlFlow.builder.analysis.NullabilityKey.class}"/>
        </annotation>
    </item>
    <item name='android.support.v7.widget.RecyclerView.LayoutManager void addView(android.view.View) 0'>
        <annotation name='org.jetbrains.annotations.NotNull'/>
    </item>
    <item name='android.support.v7.widget.GridLayoutManager void onInitializeAccessibilityNodeInfoForItem(android.support.v7.widget.RecyclerView.Recycler, android.support.v7.widget.RecyclerView.State, android.view.View, android.support.v4.view.accessibility.AccessibilityNodeInfoCompat) 3'>
        <annotation name='org.jetbrains.annotations.NotNull'/>
        <annotation name='org.jetbrains.kannotator.runtime.annotations.Propagated'>
            <val name="value" val="{org.jetbrains.kannotator.controlFlow.builder.analysis.NullabilityKey.class}"/>
        </annotation>
    </item>
    <item name='android.support.v7.widget.RecyclerView android.view.ViewGroup.LayoutParams generateLayoutParams(android.util.AttributeSet)'>
        <annotation name='org.jetbrains.annotations.NotNull'/>
    </item>
    <item name='android.support.v7.widget.LinearLayoutManager void onDetachedFromWindow(android.support.v7.widget.RecyclerView, android.support.v7.widget.RecyclerView.Recycler) 0'>
        <annotation name='org.jetbrains.annotations.NotNull'/>
        <annotation name='org.jetbrains.kannotator.runtime.annotations.Propagated'>
            <val name="value" val="{org.jetbrains.kannotator.controlFlow.builder.analysis.NullabilityKey.class}"/>
        </annotation>
    </item>
    <item name='android.support.v7.widget.RecyclerView android.view.ViewGroup.LayoutParams generateLayoutParams(android.view.ViewGroup.LayoutParams)'>
        <annotation name='org.jetbrains.annotations.NotNull'/>
    </item>
    <item name='android.support.v7.widget.SnapHelper int[] calculateDistanceToFinalSnap(android.support.v7.widget.RecyclerView.LayoutManager, android.view.View)'>
        <annotation name='org.jetbrains.annotations.NotNull'/>
        <annotation name='org.jetbrains.kannotator.runtime.annotations.Propagated'>
            <val name="value" val="{org.jetbrains.kannotator.controlFlow.builder.analysis.NullabilityKey.class}"/>
        </annotation>
    </item>
    <item name='android.support.v7.widget.RecyclerView.ItemAnimator boolean canReuseUpdatedViewHolder(android.support.v7.widget.RecyclerView.ViewHolder, java.util.List&lt;java.lang.Object&gt;) 1'>
        <annotation name='org.jetbrains.annotations.NotNull'/>
        <annotation name='org.jetbrains.kannotator.runtime.annotations.Propagated'>
            <val name="value" val="{org.jetbrains.kannotator.controlFlow.builder.analysis.NullabilityKey.class}"/>
        </annotation>
    </item>
    <item name='android.support.v7.widget.SimpleItemAnimator boolean animateAdd(android.support.v7.widget.RecyclerView.ViewHolder) 0'>
        <annotation name='org.jetbrains.annotations.NotNull'/>
        <annotation name='org.jetbrains.kannotator.runtime.annotations.Propagated'>
            <val name="value" val="{org.jetbrains.kannotator.controlFlow.builder.analysis.NullabilityKey.class}"/>
        </annotation>
    </item>
    <item name='android.support.v7.widget.RecyclerView.SmoothScroller void normalize(android.graphics.PointF) 0'>
        <annotation name='org.jetbrains.annotations.NotNull'/>
    </item>
    <item name='android.support.v7.widget.StaggeredGridLayoutManager int[] findLastVisibleItemPositions(int[])'>
        <annotation name='org.jetbrains.annotations.NotNull'/>
    </item>
    <item name='android.support.v7.widget.LinearSmoothScroller void updateActionForInterimTarget(android.support.v7.widget.RecyclerView.SmoothScroller.Action) 0'>
        <annotation name='org.jetbrains.annotations.NotNull'/>
    </item>
    <item name='android.support.v7.widget.GridLayoutManager void setMeasuredDimension(android.graphics.Rect, int, int) 0'>
        <annotation name='org.jetbrains.annotations.NotNull'/>
    </item>
    <item name='android.support.v7.widget.LinearSnapHelper int findTargetSnapPosition(android.support.v7.widget.RecyclerView.LayoutManager, int, int) 0'>
        <annotation name='org.jetbrains.annotations.NotNull'/>
        <annotation name='org.jetbrains.kannotator.runtime.annotations.Propagated'>
            <val name="value" val="{org.jetbrains.kannotator.controlFlow.builder.analysis.NullabilityKey.class}"/>
        </annotation>
    </item>
    <item name='android.support.v7.widget.RecyclerView.LayoutManager int getDecoratedRight(android.view.View) 0'>
        <annotation name='org.jetbrains.annotations.NotNull'/>
    </item>
    <item name='android.support.v7.widget.LinearSnapHelper int[] calculateDistanceToFinalSnap(android.support.v7.widget.RecyclerView.LayoutManager, android.view.View) 0'>
        <annotation name='org.jetbrains.annotations.NotNull'/>
    </item>
    <item name='android.support.v7.widget.OrientationHelper android.support.v7.widget.OrientationHelper createHorizontalHelper(android.support.v7.widget.RecyclerView.LayoutManager)'>
        <annotation name='org.jetbrains.annotations.NotNull'/>
    </item>
    <item name='android.support.v7.widget.LinearSmoothScroller float calculateSpeedPerPixel(android.util.DisplayMetrics) 0'>
        <annotation name='org.jetbrains.annotations.NotNull'/>
    </item>
    <item name='android.support.v7.widget.PagerSnapHelper android.view.View findSnapView(android.support.v7.widget.RecyclerView.LayoutManager) 0'>
        <annotation name='org.jetbrains.annotations.NotNull'/>
    </item>
    <item name='android.support.v7.widget.RecyclerView.LayoutManager void getDecoratedBoundsWithMargins(android.view.View, android.graphics.Rect) 0'>
        <annotation name='org.jetbrains.annotations.NotNull'/>
    </item>
    <item name='android.support.v7.widget.DefaultItemAnimator void endAnimation(android.support.v7.widget.RecyclerView.ViewHolder) 0'>
        <annotation name='org.jetbrains.annotations.NotNull'/>
    </item>
    <item name='android.support.v7.widget.RecyclerView boolean requestChildRectangleOnScreen(android.view.View, android.graphics.Rect, boolean) 0'>
        <annotation name='org.jetbrains.annotations.NotNull'/>
    </item>
    <item name='android.support.v7.widget.DefaultItemAnimator boolean animateMove(android.support.v7.widget.RecyclerView.ViewHolder, int, int, int, int) 0'>
        <annotation name='org.jetbrains.annotations.NotNull'/>
    </item>
    <item name='android.support.v7.widget.RecyclerView android.support.v7.widget.RecyclerView.ViewHolder getChildViewHolder(android.view.View) 0'>
        <annotation name='org.jetbrains.annotations.NotNull'/>
    </item>
    <item name='android.support.v7.widget.RecyclerView.ItemAnimator.ItemHolderInfo android.support.v7.widget.RecyclerView.ItemAnimator.ItemHolderInfo setFrom(android.support.v7.widget.RecyclerView.ViewHolder)'>
        <annotation name='org.jetbrains.annotations.NotNull'/>
    </item>
    <item name='android.support.v7.widget.RecyclerView.LayoutManager int getPosition(android.view.View) 0'>
        <annotation name='org.jetbrains.annotations.NotNull'/>
    </item>
    <item name='android.support.v7.widget.OrientationHelper android.support.v7.widget.OrientationHelper createVerticalHelper(android.support.v7.widget.RecyclerView.LayoutManager)'>
        <annotation name='org.jetbrains.annotations.NotNull'/>
    </item>
    <item name='android.support.v7.widget.RecyclerView.LayoutManager int getDecoratedTop(android.view.View) 0'>
        <annotation name='org.jetbrains.annotations.NotNull'/>
    </item>
    <item name='android.support.v7.widget.RecyclerView android.os.Parcelable onSaveInstanceState()'>
        <annotation name='org.jetbrains.annotations.NotNull'/>
    </item>
    <item name='android.support.v7.widget.SnapHelper int[] calculateScrollDistance(int, int)'>
        <annotation name='org.jetbrains.annotations.NotNull'/>
    </item>
    <item name='android.support.v7.widget.RecyclerView.LayoutManager void onInitializeAccessibilityNodeInfoForItem(android.support.v7.widget.RecyclerView.Recycler, android.support.v7.widget.RecyclerView.State, android.view.View, android.support.v4.view.accessibility.AccessibilityNodeInfoCompat) 3'>
        <annotation name='org.jetbrains.annotations.NotNull'/>
    </item>
    <item name='android.support.v7.widget.LinearLayoutManager android.support.v7.widget.RecyclerView.LayoutParams generateDefaultLayoutParams()'>
        <annotation name='org.jetbrains.annotations.NotNull'/>
    </item>
    <item name='android.support.v7.widget.RecyclerView.LayoutManager boolean requestChildRectangleOnScreen(android.support.v7.widget.RecyclerView, android.view.View, android.graphics.Rect, boolean, boolean) 1'>
        <annotation name='org.jetbrains.annotations.NotNull'/>
    </item>
    <item name='android.support.v7.widget.SimpleItemAnimator boolean animatePersistence(android.support.v7.widget.RecyclerView.ViewHolder, android.support.v7.widget.RecyclerView.ItemAnimator.ItemHolderInfo, android.support.v7.widget.RecyclerView.ItemAnimator.ItemHolderInfo) 2'>
        <annotation name='org.jetbrains.annotations.NotNull'/>
    </item>
    <item name='android.support.v7.widget.OrientationHelper int getDecoratedEnd(android.view.View) 0'>
        <annotation name='org.jetbrains.annotations.NotNull'/>
        <annotation name='org.jetbrains.kannotator.runtime.annotations.Propagated'>
            <val name="value" val="{org.jetbrains.kannotator.controlFlow.builder.analysis.NullabilityKey.class}"/>
        </annotation>
    </item>
    <item name='android.support.v7.widget.LinearSmoothScroller LinearSmoothScroller(android.content.Context) 0'>
        <annotation name='org.jetbrains.annotations.NotNull'/>
    </item>
    <item name='android.support.v7.widget.RecyclerView.LayoutManager int getTopDecorationHeight(android.view.View) 0'>
        <annotation name='org.jetbrains.annotations.NotNull'/>
    </item>
    <item name='android.support.v7.widget.RecyclerView.LayoutManager void getDecoratedBoundsWithMargins(android.view.View, android.graphics.Rect) 1'>
        <annotation name='org.jetbrains.annotations.NotNull'/>
    </item>
    <item name='android.support.v7.widget.RecyclerView.OnChildAttachStateChangeListener void onChildViewDetachedFromWindow(android.view.View) 0'>
        <annotation name='org.jetbrains.annotations.NotNull'/>
        <annotation name='org.jetbrains.kannotator.runtime.annotations.Propagated'>
            <val name="value" val="{org.jetbrains.kannotator.controlFlow.builder.analysis.NullabilityKey.class}"/>
        </annotation>
    </item>
    <item name='android.support.v7.widget.GridLayoutManager android.support.v7.widget.RecyclerView.LayoutParams generateLayoutParams(android.view.ViewGroup.LayoutParams)'>
        <annotation name='org.jetbrains.annotations.NotNull'/>
    </item>
    <item name='android.support.v7.widget.RecyclerView void removeDetachedView(android.view.View, boolean) 0'>
        <annotation name='org.jetbrains.annotations.NotNull'/>
    </item>
    <item name='android.support.v7.widget.StaggeredGridLayoutManager android.support.v7.widget.RecyclerView.LayoutParams generateLayoutParams(android.view.ViewGroup.LayoutParams)'>
        <annotation name='org.jetbrains.annotations.NotNull'/>
    </item>
    <item name='android.support.v7.widget.RecyclerView.ItemDecoration void getItemOffsets(android.graphics.Rect, int, android.support.v7.widget.RecyclerView) 0'>
        <annotation name='org.jetbrains.annotations.NotNull'/>
    </item>
    <item name='android.support.v7.widget.RecyclerView.LayoutManager android.support.v7.widget.RecyclerView.LayoutManager.Properties getProperties(android.content.Context, android.util.AttributeSet, int, int)'>
        <annotation name='org.jetbrains.annotations.NotNull'/>
    </item>
    <item name='android.support.v7.widget.DefaultItemAnimator boolean canReuseUpdatedViewHolder(android.support.v7.widget.RecyclerView.ViewHolder, java.util.List&lt;java.lang.Object&gt;) 1'>
        <annotation name='org.jetbrains.annotations.NotNull'/>
    </item>
    <item name='android.support.v7.widget.RecyclerView.LayoutManager void attachView(android.view.View, int) 0'>
        <annotation name='org.jetbrains.annotations.NotNull'/>
    </item>
    <item name='android.support.v7.widget.RecyclerView.LayoutManager void measureChild(android.view.View, int, int) 0'>
        <annotation name='org.jetbrains.annotations.NotNull'/>
    </item>
    <item name='android.support.v7.widget.LinearLayoutManager.SavedState CREATOR'>
        <annotation name='org.jetbrains.annotations.NotNull'/>
    </item>
    <item name='android.support.v7.widget.LinearSmoothScroller mDecelerateInterpolator'>
        <annotation name='org.jetbrains.annotations.NotNull'/>
    </item>
    <item name='android.support.v7.widget.LinearSnapHelper android.view.View findSnapView(android.support.v7.widget.RecyclerView.LayoutManager) 0'>
        <annotation name='org.jetbrains.annotations.NotNull'/>
    </item>
    <item name='android.support.v7.widget.SimpleItemAnimator boolean animateDisappearance(android.support.v7.widget.RecyclerView.ViewHolder, android.support.v7.widget.RecyclerView.ItemAnimator.ItemHolderInfo, android.support.v7.widget.RecyclerView.ItemAnimator.ItemHolderInfo) 0'>
        <annotation name='org.jetbrains.annotations.NotNull'/>
    </item>
    <item name='android.support.v7.widget.RecyclerView.LayoutManager void onDetachedFromWindow(android.support.v7.widget.RecyclerView, android.support.v7.widget.RecyclerView.Recycler) 0'>
        <annotation name='org.jetbrains.annotations.NotNull'/>
        <annotation name='org.jetbrains.kannotator.runtime.annotations.Propagated'>
            <val name="value" val="{org.jetbrains.kannotator.controlFlow.builder.analysis.NullabilityKey.class}"/>
        </annotation>
    </item>
    <item name='android.support.v7.widget.RecyclerViewAccessibilityDelegate void onInitializeAccessibilityEvent(android.view.View, android.view.accessibility.AccessibilityEvent) 1'>
        <annotation name='org.jetbrains.annotations.NotNull'/>
    </item>
    <item name='android.support.v7.widget.DefaultItemAnimator boolean animateAdd(android.support.v7.widget.RecyclerView.ViewHolder) 0'>
        <annotation name='org.jetbrains.annotations.NotNull'/>
    </item>
    <item name='android.support.v7.widget.GridLayoutManager void onLayoutChildren(android.support.v7.widget.RecyclerView.Recycler, android.support.v7.widget.RecyclerView.State) 1'>
        <annotation name='org.jetbrains.annotations.NotNull'/>
    </item>
    <item name='android.support.v7.widget.OrientationHelper void offsetChild(android.view.View, int) 0'>
        <annotation name='org.jetbrains.annotations.NotNull'/>
        <annotation name='org.jetbrains.kannotator.runtime.annotations.Propagated'>
            <val name="value" val="{org.jetbrains.kannotator.controlFlow.builder.analysis.NullabilityKey.class}"/>
        </annotation>
    </item>
    <item name='android.support.v7.widget.RecyclerView android.view.View findContainingItemView(android.view.View) 0'>
        <annotation name='org.jetbrains.annotations.NotNull'/>
    </item>
    <item name='android.support.v7.widget.OrientationHelper int getTransformedEndWithDecoration(android.view.View) 0'>
        <annotation name='org.jetbrains.annotations.NotNull'/>
        <annotation name='org.jetbrains.kannotator.runtime.annotations.Propagated'>
            <val name="value" val="{org.jetbrains.kannotator.controlFlow.builder.analysis.NullabilityKey.class}"/>
        </annotation>
    </item>
    <item name='android.support.v7.widget.StaggeredGridLayoutManager void onDetachedFromWindow(android.support.v7.widget.RecyclerView, android.support.v7.widget.RecyclerView.Recycler) 0'>
        <annotation name='org.jetbrains.annotations.NotNull'/>
    </item>
    <item name='android.support.v7.widget.SimpleItemAnimator boolean animatePersistence(android.support.v7.widget.RecyclerView.ViewHolder, android.support.v7.widget.RecyclerView.ItemAnimator.ItemHolderInfo, android.support.v7.widget.RecyclerView.ItemAnimator.ItemHolderInfo) 1'>
        <annotation name='org.jetbrains.annotations.NotNull'/>
    </item>
    <item name='android.support.v7.widget.RecyclerView.LayoutManager android.support.v7.widget.RecyclerView.LayoutParams generateLayoutParams(android.content.Context, android.util.AttributeSet)'>
        <annotation name='org.jetbrains.annotations.NotNull'/>
    </item>
    <item name='android.support.v7.widget.RecyclerView.LayoutManager android.support.v7.widget.RecyclerView.LayoutParams generateLayoutParams(android.view.ViewGroup.LayoutParams)'>
        <annotation name='org.jetbrains.annotations.NotNull'/>
    </item>
    <item name='android.support.v7.widget.RecyclerView.LayoutManager void attachView(android.view.View) 0'>
        <annotation name='org.jetbrains.annotations.NotNull'/>
    </item>
    <item name='android.support.v7.widget.DividerItemDecoration void setDrawable(android.graphics.drawable.Drawable) 0'>
        <annotation name='org.jetbrains.annotations.NotNull'/>
    </item>
    <item name='android.support.v7.widget.OrientationHelper int getDecoratedMeasurementInOther(android.view.View) 0'>
        <annotation name='org.jetbrains.annotations.NotNull'/>
        <annotation name='org.jetbrains.kannotator.runtime.annotations.Propagated'>
            <val name="value" val="{org.jetbrains.kannotator.controlFlow.builder.analysis.NullabilityKey.class}"/>
        </annotation>
    </item>
    <item name='android.support.v7.widget.OrientationHelper int getDecoratedStart(android.view.View) 0'>
        <annotation name='org.jetbrains.annotations.NotNull'/>
        <annotation name='org.jetbrains.kannotator.runtime.annotations.Propagated'>
            <val name="value" val="{org.jetbrains.kannotator.controlFlow.builder.analysis.NullabilityKey.class}"/>
        </annotation>
    </item>
    <item name='android.support.v7.widget.StaggeredGridLayoutManager.SavedState void writeToParcel(android.os.Parcel, int) 0'>
        <annotation name='org.jetbrains.annotations.NotNull'/>
    </item>
    <item name='android.support.v7.widget.RecyclerView.OnItemTouchListener boolean onInterceptTouchEvent(android.support.v7.widget.RecyclerView, android.view.MotionEvent) 1'>
        <annotation name='org.jetbrains.annotations.NotNull'/>
        <annotation name='org.jetbrains.kannotator.runtime.annotations.Propagated'>
            <val name="value" val="{org.jetbrains.kannotator.controlFlow.builder.analysis.NullabilityKey.class}"/>
        </annotation>
    </item>
    <item name='android.support.v7.widget.LinearLayoutManager void smoothScrollToPosition(android.support.v7.widget.RecyclerView, android.support.v7.widget.RecyclerView.State, int) 0'>
        <annotation name='org.jetbrains.annotations.NotNull'/>
    </item>
    <item name='android.support.v7.widget.RecyclerView.Adapter VH createViewHolder(android.view.ViewGroup, int)'>
        <annotation name='org.jetbrains.annotations.NotNull'/>
    </item>
    <item name='android.support.v7.widget.RecyclerView.Recycler android.view.View getViewForPosition(int)'>
        <annotation name='org.jetbrains.annotations.NotNull'/>
    </item>
    <item name='android.support.v7.widget.LinearLayoutManager.SavedState void writeToParcel(android.os.Parcel, int) 0'>
        <annotation name='org.jetbrains.annotations.NotNull'/>
    </item>
    <item name='android.support.v7.widget.RecyclerView.ItemDecoration void onDraw(android.graphics.Canvas, android.support.v7.widget.RecyclerView, android.support.v7.widget.RecyclerView.State) 1'>
        <annotation name='org.jetbrains.annotations.NotNull'/>
        <annotation name='org.jetbrains.kannotator.runtime.annotations.Propagated'>
            <val name="value" val="{org.jetbrains.kannotator.controlFlow.builder.analysis.NullabilityKey.class}"/>
        </annotation>
    </item>
    <item name='android.support.v7.widget.RecyclerView.LayoutManager int getDecoratedMeasuredWidth(android.view.View) 0'>
        <annotation name='org.jetbrains.annotations.NotNull'/>
    </item>
    <item name='android.support.v7.widget.SnapHelper android.view.View findSnapView(android.support.v7.widget.RecyclerView.LayoutManager) 0'>
        <annotation name='org.jetbrains.annotations.NotNull'/>
        <annotation name='org.jetbrains.kannotator.runtime.annotations.Propagated'>
            <val name="value" val="{org.jetbrains.kannotator.controlFlow.builder.analysis.NullabilityKey.class}"/>
        </annotation>
    </item>
    <item name='android.support.v7.widget.SimpleItemAnimator boolean animateDisappearance(android.support.v7.widget.RecyclerView.ViewHolder, android.support.v7.widget.RecyclerView.ItemAnimator.ItemHolderInfo, android.support.v7.widget.RecyclerView.ItemAnimator.ItemHolderInfo) 1'>
        <annotation name='org.jetbrains.annotations.NotNull'/>
    </item>
    <item name='android.support.v7.widget.StaggeredGridLayoutManager android.os.Parcelable onSaveInstanceState()'>
        <annotation name='org.jetbrains.annotations.NotNull'/>
    </item>
    <item name='android.support.v7.widget.StaggeredGridLayoutManager android.support.v7.widget.RecyclerView.LayoutParams generateDefaultLayoutParams()'>
        <annotation name='org.jetbrains.annotations.NotNull'/>
    </item>
    <item name='android.support.v7.widget.OrientationHelper android.support.v7.widget.OrientationHelper createOrientationHelper(android.support.v7.widget.RecyclerView.LayoutManager, int)'>
        <annotation name='org.jetbrains.annotations.NotNull'/>
    </item>
    <item name='android.support.v7.widget.RecyclerView.ViewHolder itemView'>
        <annotation name='org.jetbrains.annotations.NotNull'/>
    </item>
    <item name='android.support.v7.widget.RecyclerView boolean requestChildRectangleOnScreen(android.view.View, android.graphics.Rect, boolean) 1'>
        <annotation name='org.jetbrains.annotations.NotNull'/>
    </item>
    <item name='android.support.v7.widget.RecyclerView.LayoutManager void addDisappearingView(android.view.View) 0'>
        <annotation name='org.jetbrains.annotations.NotNull'/>
    </item>
    <item name='android.support.v7.widget.LinearLayoutManager int getExtraLayoutSpace(android.support.v7.widget.RecyclerView.State) 0'>
        <annotation name='org.jetbrains.annotations.NotNull'/>
    </item>
    <item name='android.support.v7.widget.RecyclerView.LayoutManager int getBottomDecorationHeight(android.view.View) 0'>
        <annotation name='org.jetbrains.annotations.NotNull'/>
    </item>
    <item name='android.support.v7.widget.RecyclerView.ItemAnimator android.support.v7.widget.RecyclerView.ItemAnimator.ItemHolderInfo recordPostLayoutInformation(android.support.v7.widget.RecyclerView.State, android.support.v7.widget.RecyclerView.ViewHolder) 1'>
        <annotation name='org.jetbrains.annotations.NotNull'/>
    </item>
    <item name='android.support.v7.widget.GridLayoutManager android.support.v7.widget.RecyclerView.LayoutParams generateDefaultLayoutParams()'>
        <annotation name='org.jetbrains.annotations.NotNull'/>
    </item>
    <item name='android.support.v7.widget.RecyclerView.ItemAnimator void endAnimation(android.support.v7.widget.RecyclerView.ViewHolder) 0'>
        <annotation name='org.jetbrains.annotations.NotNull'/>
        <annotation name='org.jetbrains.kannotator.runtime.annotations.Propagated'>
            <val name="value" val="{org.jetbrains.kannotator.controlFlow.builder.analysis.NullabilityKey.class}"/>
        </annotation>
    </item>
    <item name='android.support.v7.widget.RecyclerView.LayoutManager int getDecoratedMeasuredHeight(android.view.View) 0'>
        <annotation name='org.jetbrains.annotations.NotNull'/>
    </item>
    <item name='android.support.v7.widget.RecyclerView.LayoutManager void getTransformedBoundingBox(android.view.View, boolean, android.graphics.Rect) 2'>
        <annotation name='org.jetbrains.annotations.NotNull'/>
    </item>
    <item name='android.support.v7.widget.LinearSnapHelper int[] calculateDistanceToFinalSnap(android.support.v7.widget.RecyclerView.LayoutManager, android.view.View)'>
        <annotation name='org.jetbrains.annotations.NotNull'/>
    </item>
    <item name='android.support.v7.widget.SnapHelper int[] calculateDistanceToFinalSnap(android.support.v7.widget.RecyclerView.LayoutManager, android.view.View) 0'>
        <annotation name='org.jetbrains.annotations.NotNull'/>
        <annotation name='org.jetbrains.kannotator.runtime.annotations.Propagated'>
            <val name="value" val="{org.jetbrains.kannotator.controlFlow.builder.analysis.NullabilityKey.class}"/>
        </annotation>
    </item>
</root>
